[
  {
    "notice_code": "11000NTC199604195967",
    "notice_no": "1996-90",
    "notice_date": "1996-04-19",
    "title": "도시계획용도지역변경결정및상세계획구역결정",
    "content": "1. 도시계획법 제12조 및 같은법시행령 제6조의 규정에 의하여 도시계획 용도지역변경결정 및 상세계획구역 결정을 하였기 도시계획법 제12조제4항 및 같은법시행령 제8조의 규정에 따라 이를 고시합니다. 2. 관계도서는 서울특별시 도시계획국 도시계획과와 서초구 도시정비국 도시정비과에 비치하여 이해관계인에게 보입니다. 1996년 4월 19일 서울특별시장",
    "organ_code": "6110000",
    "organ_name": "서울특별시",
    "notice_type": "지구단위계획",
    "classify_g": "",
    "classify_m": "",
    "site_code": "11000",
    "site_name": "",
    "location": "서초구 방배동444일대",
    "doc_url": "",
    "page_url": "https://urban.seoul.go.kr/view/html/PMNU4030200001?noticeCode=11000NTC199604195967",
    "center_grade": null,
    "center_name": null,
    "category": "지구단위계획",
    "zone_name": "남현지구중심 상세계획구역",
    "area": 44340
  }
]