[
  {
    "notice_code": "11000NTC200207192899",
    "notice_no": "2002-38",
    "notice_date": "2002-07-19",
    "title": "지구단위계획구역실효",
    "content": "도시계획법 제44조 및 부칙 제7조의 규정에 의거 우리구 관내 문정지구의 8개소의 지구단위계획구역지정에 관한 도시계획결정의 효력이 상실되었기 같은법 시행령 제44조의 규정에 의거 다음과 같이 지구단위계획구역 지정을 실효 고시합니다. 2002년 7월19일 송파구청장",
    "organ_code": "3230000",
    "organ_name": "송파구",
    "notice_type": "지구단위계획",
    "classify_g": "",
    "classify_m": "",
    "site_code": "11000",
    "site_name": "",
    "location": "가락동 96-1번지 일대",
    "doc_url": "",
    "page_url": "https://urban.seoul.go.kr/view/html/PMNU4030200001?noticeCode=11000NTC200207192899",
    "center_grade": null,
    "center_name": null,
    "category": "지구단위계획",
    "zone_name": "가락1지구",
    "area": 0
  }
]