[
  {
    "notice_code": "11000NTC200404066023",
    "notice_no": "2004-93",
    "notice_date": "2004-04-06",
    "title": "상신아파트재건축정비구역지정",
    "content": "서울특별시 동작구 사당동 1000-8번지 일대를 도시및주거환경정비법 제4조제2항의 규정에 의하여 상신아파트 주택재건축정비구역으로 지정하고 같은 법 제4조제3항의 규정에 따라 이를 고시합니다. 2004년 4월 6일 서울특별시장",
    "organ_code": "6110000",
    "organ_name": "서울특별시",
    "notice_type": "지구단위계획",
    "classify_g": "",
    "classify_m": "",
    "site_code": "11590",
    "site_name": "",
    "location": "사당동 1000-8번지 일대",
    "doc_url": "",
    "page_url": "https://urban.seoul.go.kr/view/html/PMNU4030200001?noticeCode=11000NTC200404066023",
    "center_grade": "지역중심",
    "center_name": "사당·이수",
    "category": "지구단위계획",
    "zone_name": "상신아파트 재건축 정비구역(휴먼시아)",
    "area": 21026.4
  },
  {
    "notice_code": "11000NTC200404065998",
    "notice_no": "2004-95",
    "notice_date": "2004-04-06",
    "title": "제기제2주택재개발구역변경지정",
    "content": "건설부고시 제1994-234호(1994. 7. 8)로 구역지정되고 서울특별시고시 제1994-460호(1995. 1. 7)로 구역변경지정된 동대문구 제기동 122번지 일대 제기제2주택재개발구역에 대하여 도시및주거환경정비법 제4조제2항 및 같은법 부칙 제7조의 규정에 의하여 구역변경지정하고 같은법 제4조제3항의 규정에 의하여 이를 고시합니다. 2004년 4월 6일 서울특별시장",
    "organ_code": "6110000",
    "organ_name": "서울특별시",
    "notice_type": "정비사업구역계",
    "classify_g": "",
    "classify_m": "",
    "site_code": "11000",
    "site_name": "",
    "location": "동대문구 제기동 122번지 일대",
    "doc_url": "",
    "page_url": "https://urban.seoul.go.kr/view/html/PMNU4030600001?noticeCode=11000NTC200404065998",
    "center_grade": "지역중심",
    "center_name": "동대문",
    "category": "정비사업구역계"
  }
]