[
  {
    "notice_code": "11000NTC200507148592",
    "notice_no": "2005-208",
    "notice_date": "2005-07-14",
    "title": "도시관리계획(뚝섬주변지역제1종지구단위계획구역)결정",
    "content": "국토의계획및이용에관한법률 제30조 및 같은법시행령 제25조의 규정에 따라 서울특별시 성동구 성수동 1가 685-580번지 일대에 대하여 다음과 같이 도시관리계획(뚝섬주변지역 제1종지구단위계획구역)을 결정하고 이를 고시합니다. 2005년 7월 14일 서울특별시장",
    "organ_code": "6110000",
    "organ_name": "서울특별시",
    "notice_type": "지구단위계획",
    "classify_g": "",
    "classify_m": "",
    "site_code": "11000",
    "site_name": "",
    "location": "서울특별시 성동구 성수동 1가 685-580번지 일대",
    "doc_url": "",
    "page_url": "https://urban.seoul.go.kr/view/html/PMNU4030200001?noticeCode=11000NTC200507148592",
    "center_grade": "지역중심",
    "center_name": "성수",
    "category": "지구단위계획",
    "zone_name": "뚝섬주변지역 제1종지구단위계획구역",
    "area": 436240
  }
]