[
  {
    "notice_code": "11000NTC200701040671",
    "notice_no": "2006-460",
    "notice_date": "2007-01-04",
    "title": "서울동남권 유통단지변경지정 및 실시계획변경 승인",
    "content": "서울특별시고시 제2004-391호(2004.11. 25)로 유통단지 지정되고, 서울특별시고시 제2005-339(2005.11.10)호로 실시계획승인 된 서울동남권유통단지에 대하여 ?유통단지 개발촉진법? 제5조 및 제11조의 규정에 의하여 유통단지변경지정 및 실시계획을 변경승인 함에 따라 같은 법 제6조 및 제12조의 규정에 의하여 이를 고시합니다. 아울러, 관계서류는 서울특별시 균형발전추진본부 이주사업담당관(전화：2171-2525) 및 송파구 교통행정과(전화：410-3365~9), SH공사 사업2본부 개발계획팀(전화：3410- 7290~1)에 비치하고 이해관계인 및 일반인에게 보입니다. 2007년  1월  4일 서 울 특 별 시 장",
    "organ_code": "6110000",
    "organ_name": "서울특별시",
    "notice_type": "지구단위계획",
    "classify_g": "",
    "classify_m": "",
    "site_code": "11000",
    "site_name": "",
    "location": "서울시 송파구 문정동 280 일원",
    "doc_url": "https://urban.seoul.go.kr/UpisArchive/DATA/PM/pdf/%EC%84%9C%EC%9A%B8%ED%8A%B9%EB%B3%84%EC%8B%9C2006-460.PDF",
    "page_url": "https://urban.seoul.go.kr/view/html/PMNU4030200001?noticeCode=11000NTC200701040671",
    "center_grade": "지역중심",
    "center_name": "수서·문정",
    "category": "지구단위계획",
    "zone_name": "서울동남권유통단지 제1종 지구단위계획구역",
    "area": 512766
  }
]