[
  {
    "notice_code": "11000NTC200902112770",
    "notice_no": "2009-13",
    "notice_date": "2009-02-11",
    "title": "구로온수연립 주택재건축 정비구역 변경 지정 및 지형도면 작성",
    "content": "서울특별시고시 제2005-429호(2005.12. 29.), 구로구고시 제2006-6(2006.1.9)호, 서울특별시고시 제2008-222(2008.7.3)호, 서울특별시구로구고시 제2008-55(2008.8. 28)호로 정비구역지정(및 변경지정)된 구로구 온수동 125번지 일대에 대하여 「도시 및 주거환경 정비법」제4조 제1항, 동법 시행령 제12조  규정에 따라 정비구역을 변경 지정하고, 같은 법 제4조 제4항 및 「토지이용규제기본법」제8조의 규정에 의해 정비구역 변경 지정 및 지형도면을 작성 고시합니다.   2009년 2월  일    구  로  구  청  장",
    "organ_code": "3160000",
    "organ_name": "구로구",
    "notice_type": "정비사업구역계",
    "classify_g": "",
    "classify_m": "",
    "site_code": "11000",
    "site_name": "",
    "location": "구로구 온수동 125번지 일대",
    "doc_url": "https://urban.seoul.go.kr/UpisArchive/DATA/PM/pdf/%EA%B5%AC%EB%A1%9C%EA%B5%AC2009-13.HWP",
    "page_url": "https://urban.seoul.go.kr/view/html/PMNU4030600001?noticeCode=11000NTC200902112770",
    "center_grade": null,
    "center_name": null,
    "category": "정비사업구역계"
  }
]