[
  {
    "notice_code": "11000NTC201706228177",
    "notice_no": "2017-218",
    "notice_date": "2017-06-22",
    "title": "금천구 독산동 금하마을 저비구역 지정 및 지형도면 고시",
    "content": "금천구 독산동 1100번지 일대에 대하여 주거환경관리사업 정비구역 지정하고, 지형도면을 고시합니다.",
    "organ_code": "6110000",
    "organ_name": "서울특별시",
    "notice_type": "정비사업구역계",
    "classify_g": "",
    "classify_m": "",
    "site_code": "11000",
    "site_name": "",
    "location": "금천구 독산동 1100 일원",
    "doc_url": "https://urban.seoul.go.kr/UpisArchive/DATA/PM/pdf/%EC%84%9C%EC%9A%B8%ED%8A%B9%EB%B3%84%EC%8B%9C2017-218.PDF",
    "page_url": "https://urban.seoul.go.kr/view/html/PMNU4030600001?noticeCode=11000NTC201706228177",
    "center_grade": null,
    "center_name": null,
    "category": "정비사업구역계"
  }
]