[
  {
    "notice_code": "11000NTC201907041037",
    "notice_no": "2019-214",
    "notice_date": "2019-07-04",
    "title": "도시관리계획(지구단위계획구역 지정 및 계획수립)결정(변경)및 지형도면고시-광진구 구의동 587-62번지 일원 역세권 청년주택-",
    "content": "서울특별시 광진구 구의동 587-62일원 『도시관리계획(광진구 구의동 587-62 일원 역세권 청년주택 지구단위계획구역 지정 및 계획수립) 결정(변경)』에 대하여 「민간임대주택에 관한 특별법」 제29조 및 「서울특별시 역세권 청년주택 공급 지원에 관한 조례」 제9조에 따라 2019년 제3차 서울특별시 도시·건축공동위원회(역세권 청년주택 수권분과위원회) (2019. 04. 04.) 심의 및 2109년 제5차 서울특별시 도시·건축공동위원회(역세권 청년주택 수권분과위원회) (2019. 06. 21.) 보고를  거쳐「국토의 계획 및 이용에 관한 법률」 제30조 및 같은 법 시행령 제25조 규정에 따라 결정(변경)하고 「토지이용규제 기본법」 제8조 및 같은 법 시행령 제7조에 따라 지형도면을 고시합니다.",
    "organ_code": "6110000",
    "organ_name": "서울특별시",
    "notice_type": "지구단위계획",
    "classify_g": "",
    "classify_m": "",
    "site_code": "11000",
    "site_name": "",
    "location": "광진구 구의동 587-62",
    "doc_url": "https://urban.seoul.go.kr/UpisArchive/DATA/PM/pdf/11000NTC201907041037/%EC%84%9C%EC%9A%B8%ED%8A%B9%EB%B3%84%EC%8B%9C%EA%B3%A0%EC%8B%9C%20%EC%A0%9C2019-214%ED%98%B8%20%EB%8F%84%EC%8B%9C%EA%B4%80%EB%A6%AC%EA%B3%84%ED%9A%8D%28%EC%A7%80%EA%B5%AC%EB%8B%A8%EC%9C%84%EA%B3%84%ED%9A%8D%EA%B5%AC%EC%97%AD%20%EC%A7%80%EC%A0%95%20%EB%B0%8F%20%EA%B3%84%ED%9A%8D%EC%88%98%EB%A6%BD%29%20%EA%B2%B0%EC%A0%95%28%EB%B3%80%EA%B2%BD%29%20%EB%B0%8F%20%EC%A7%80%ED%98%95%EB%8F%84%EB%A9%B4%20%EA%B3%A0%EC%8B%9C.pdf",
    "page_url": "https://urban.seoul.go.kr/view/html/PMNU4030200001?noticeCode=11000NTC201907041037",
    "center_grade": null,
    "center_name": null,
    "category": "지구단위계획",
    "zone_name": "광진구 구의동 587-62 일원 역세권 청년주택",
    "area": 648
  }
]