[
  {
    "notice_code": "11000NTC202305230003",
    "notice_no": "2023-174",
    "notice_date": "2023-05-11",
    "title": "성동구 마장동 339-2일원 공공지원민간임대주택(역세권 청년주택)  공급촉진지구 지정(변경).지구계획 승인(변경) 및 도시관리계획 (지구단위계획) 결정(변경) 고시",
    "content": "서울특별시고시 제2021-453호(2021.8.19.)로 공공지원민간임대주택(역세권 청년주택) 공급촉진지구 지정 및 지구계획 승인, 서울특별시고시 제2021-454호(2021.8.19.)로 사업계획 승인된 성동구 마장동 339-2일원 공공지원민간임대주택(역세권 청년주택) 공급촉진지구에 대하여 「민간임대주택에 관한 특별법」 제26조, 제28조 및 같은 법 시행령 제21조, 제24조, 「서울시 역세권 청년주택 공급 지원에 관한 조례」 제9조에 따라 공공지원민간임대주택(역세권 청년주택) 공급촉진지구 지정(변경)·지구계획 승인(변경) 및 도시관리계획(지구단위계획) 결정(변경) 고시합니다.",
    "organ_code": "6110000",
    "organ_name": "서울특별시",
    "notice_type": "지구단위계획",
    "classify_g": "",
    "classify_m": "",
    "site_code": "11000",
    "site_name": "",
    "location": "성동구 마장동 339-2일원",
    "doc_url": "https://urban.seoul.go.kr/UpisArchive/DATA/PM/pdf/11000TTC202305230003/%EC%84%9C%EC%9A%B8%ED%8A%B9%EB%B3%84%EC%8B%9C_2023-174%ED%98%B8_%EA%B3%A0%EC%8B%9C.pdf",
    "page_url": "https://urban.seoul.go.kr/view/html/PMNU4030200001?noticeCode=11000NTC202305230003",
    "center_grade": null,
    "center_name": null,
    "category": "지구단위계획",
    "zone_name": "성동구 마장동 339-2일원 공공지원민간임대주택(역세권 청년주택) 공급촉진지구 지구단위계획구역",
    "area": 3448.2
  },
  {
    "notice_code": "11230NTC202306010006",
    "notice_no": "2023-54",
    "notice_date": "2023-05-11",
    "title": "청량리제7구역 주택재개발정비사업 정비계획 및 정비구역(경미한 변경) 및 지형도면 고시",
    "content": " 서울특별시고시 제2007-310호(2007.9.6.)로 정비계획 수립 및 정비구역 지정되고, 동대문구고시 제2008-16호(2008.2.21.) 정비계획 수립 및 정비구역 변경, 제2008-87호(2008.11.20.)와 동대문구고시 제2009-5호(2009.1.29.) 정비계획 수립 및 정비구역 변경, 서울특별시고시 제2011-267호(2011.9.15.) 정비계획 수립 및 정비구역 변경, 동대문구고시 제2016-60호(2016.9.8.) 정비계획 수립 및 정비구역 변경 지정, 서울특별시고시 제2018-99호(2018.04.05.)로 정비계획 및 정비구역 변경, 동대문구고시 제2019-40호(2019.4.25.)로 정비계획 및 정비구역 변경 지정된 청량리 제7구역 주택재개발 정비구역에 대하여 측량결과 및 정비기반시설 선형변경 반영에 따른 정비계획 변경사항(경미한 변경)이 발생하여 『도시 및 주거환경 정비법』 제16조 및 동법 시행령 제13조에 근거하여 정비계획 변경(경미한 변경)을 고시하며, 『토지이용규제기본법』 제8조의 규정에 따라 지형도면을 함께 고시합니다.\n",
    "organ_code": "3050000",
    "organ_name": "동대문구",
    "notice_type": "정비사업구역계",
    "classify_g": "",
    "classify_m": "",
    "site_code": "11000",
    "site_name": "",
    "location": "동대문구 청량리동 199번지 일대",
    "doc_url": "https://urban.seoul.go.kr/UpisArchive/DATA/PM/pdf/11230NTC202306010006/%EB%8F%99%EB%8C%80%EB%AC%B8%EA%B5%AC_2023-54%ED%98%B8_%EA%B3%A0%EC%8B%9C.pdf",
    "page_url": "https://urban.seoul.go.kr/view/html/PMNU4030600001?noticeCode=11230NTC202306010006",
    "center_grade": "광역중심",
    "center_name": "청량리·왕십리",
    "category": "정비사업구역계"
  }
]