[
  {
    "notice_code": "11650NTC202502040004",
    "notice_no": "2025-22",
    "notice_date": "2025-01-31",
    "title": "도시관리계획(내방역 일대 지구단위계획구역) 결정(경미한 변경) 고시",
    "content": "서초구 방배동 875-24번지 일대 도시계획시설(철도) 결정(변경)에 대하여 「국토의 계획 및 이용에 관한 법률」 제30조, 같은법 시행령 제25조 및 「서울특별시 도시계획조례」제67조 규정에 따라 도시관리계획 결정(경미한 변경)하고 「국토의 계획 및 이용에 관한 법률」 제32조 및 「토지이용규제 기본법」 제8조 규정에 의하여 지형도면을 작성·고시합니다.",
    "organ_code": "3210000",
    "organ_name": "서초구",
    "notice_type": "결정+지적",
    "classify_g": "",
    "classify_m": "",
    "site_code": "11000",
    "site_name": "서울특별시",
    "location": "서초구 방배동 874 일대",
    "doc_url": "https://urban.seoul.go.kr/UpisArchive/DATA/PM/pdf/11650NTC202502040004/%EC%84%9C%EC%B4%88%EA%B5%AC_%EC%A0%9C2025-22%ED%98%B8_%EA%B3%A0%EC%8B%9C.pdf",
    "page_url": "https://urban.seoul.go.kr/view/html/PMNU4030100001?noticeCode=11650NTC202502040004",
    "center_grade": null,
    "center_name": null
  },
  {
    "notice_code": "11650NTC202502040003",
    "notice_no": "2025-18",
    "notice_date": "2025-01-31",
    "title": "방배 제14주택재건축 정비계획 결정(경미한 변경), 지구단위계획 결정(경미한 변경) 및 지형도면 고시",
    "content": "서울특별시고시 제2014-257호(2014.7.10.)로 정비구역지정 및 정비계획수립되고 서울특별시 서초구고시 제2016-86호(2016.9.8.), 제2017-16호(2017.2.16.), 제2017-137호(2017.10.26.), 서울특별시고시 제2022-404호(2022.10.6.)로 변경 고시된 방배 제14주택재건축 정비구역 및 정비계획에 대하여 「도시 및 주거환경정비법」(이하 ‘도시정비법’) 제16조 및 제17조에 의거 정비구역 및 정비계획 결정(경미한 변경)하고, 「국토의 계획 및 이용에 관한 법률」제50조 및 제51조에 따라 지구단위계획구역 및 지구단위계획으로 결정(경미한 변경) 고시하며, 「토지이용규제 기본법」 제8조에 따라 지형도면을 고시하고자 합니다.",
    "organ_code": "3210000",
    "organ_name": "서초구",
    "notice_type": "결정+지적",
    "classify_g": "",
    "classify_m": "",
    "site_code": "11000",
    "site_name": "서울특별시",
    "location": "서초구 방배동 975-35 일대",
    "doc_url": "https://urban.seoul.go.kr/UpisArchive/DATA/PM/pdf/11650NTC202502040003/%EC%84%9C%EC%B4%88%EA%B5%AC_%EC%A0%9C2025-18%ED%98%B8_%EA%B3%A0%EC%8B%9C.pdf",
    "page_url": "https://urban.seoul.go.kr/view/html/PMNU4030100001?noticeCode=11650NTC202502040003",
    "center_grade": null,
    "center_name": null
  },
  {
    "notice_code": "11000NTC202502180005",
    "notice_no": "2025-67",
    "notice_date": "2025-01-31",
    "title": "강남구 역삼동 828-2 일원 공공지원민간임대주택(청년안심주택) 도시관리계획(지구단위계획) 결정(경미한 변경) 고시",
    "content": "서울특별시고시 제2023-132호(2023.4.13.)로 공급촉진지구 지정 및 지구계획 승인되고, 서 울특별시고시 제2023-257호(2023.6.22.)로 공급촉진지구 지구계획 결정(변경) 고시된 강남구  역삼동 828-2 일원 공공지원민간임대주택(청년안심주택)에 대하여, 「국토의 계획 및 이용에 관 한 법률」제30조 및 같은 법 시행령 제25조 규정에 따라 도시관리계획 (경미한)변경 결정하고,  「토지이용규제기본법」제8조 규정에 따라 지형도면을 고시합니다.",
    "organ_code": "6110000",
    "organ_name": "서울특별시",
    "notice_type": "결정",
    "classify_g": "",
    "classify_m": "",
    "site_code": "11000",
    "site_name": "서울특별시",
    "location": "강남구 역삼동 828-2",
    "doc_url": "https://urban.seoul.go.kr/UpisArchive/DATA/PM/pdf/11000TTC202502180005/%EC%84%9C%EC%9A%B8%ED%8A%B9%EB%B3%84%EC%8B%9C_%EC%A0%9C2025-67%ED%98%B8_%EA%B3%A0%EC%8B%9C.pdf",
    "page_url": "https://urban.seoul.go.kr/view/html/PMNU4030100001?noticeCode=11000NTC202502180005",
    "center_grade": "도심",
    "center_name": "강남"
  },
  {
    "notice_code": "11590NTC202502110009",
    "notice_no": "2025-10",
    "notice_date": "2025-01-31",
    "title": "동작구 상도동(성대골) 관리형 주거환경개선사업 공사완료 고시",
    "content": "서울특별시고시 제2015-188호(2015.7.2.)로 정비구역 지정 및 정비계획 결정되고, 서울특별시고시 제2017-283호(2017.8.3.) 및 서울특별시동작구고시 제2021-270호(2021.11.11.)로 정비계획 결정(변경) 고시된 동작구 상도동 259-40번지 일대 성대골 관리형 주거환경개선사업에 대하여 「도시 및 주거환경정비법」 제83조제4항 및 같은 법 시행령 제74조제4항에 따라 공사 완료 고시하며,「토지이용규제 기본법」 제8조에 따라 지형도면을 고시합니다.\n아울러「도시 및 주거환경정비법」 제84조에 따라 공사완료 고시 익일 주거환경개선사업 정비구역은 해제됩니다. \n\n",
    "organ_code": "3190000",
    "organ_name": "동작구",
    "notice_type": "결정+지적+실시",
    "classify_g": "",
    "classify_m": "",
    "site_code": "11000",
    "site_name": "서울특별시",
    "location": "동작구 상도동 259-40번지 일대",
    "doc_url": "https://urban.seoul.go.kr/UpisArchive/DATA/PM/pdf/11590NTC202502110009/%EB%8F%99%EC%9E%91%EA%B5%AC_%EC%A0%9C2025-10%ED%98%B8_%EA%B3%A0%EC%8B%9C.pdf",
    "page_url": "https://urban.seoul.go.kr/view/html/PMNU4030100001?noticeCode=11590NTC202502110009",
    "center_grade": null,
    "center_name": null
  }
]